{
  "gifts": [
    {
      "id": "rose",
      "name": "玫瑰",
      "price": 10,
      "category": "romantic",
      "reaction_template": "收到玫瑰时，伴侣会脸红并说：\"谢谢你，这真让我心动...\""
    },
    {
      "id": "chocolate",
      "name": "巧克力",
      "price": 15,
      "category": "sweet",
      "reaction_template": "收到巧克力时，伴侣会开心地说：\"我最喜欢巧克力了！你真懂我~\""
    },
    {
      "id": "teddy_bear",
      "name": "泰迪熊",
      "price": 30,
      "category": "comfort",
      "reaction_template": "收到泰迪熊时，伴侣会抱住它说：\"这让我想起了你温暖的拥抱...\""
    },
    {
      "id": "necklace",
      "name": "项链",
      "price": 50,
      "category": "precious",
      "reaction_template": "收到项链时，伴侣会感动地说：\"这太珍贵了...我会永远珍惜的\""
    },
    {
      "id": "love_letter",
      "name": "情书",
      "price": 5,
      "category": "romantic",
      "reaction_template": "收到情书时，伴侣会认真阅读并回应你的真挚情感"
    }
  ]
}